webhaak/__init__.py
webhaak/incoming.py
webhaak/main.py
webhaak/tasks.py
webhaak-0.6.0.dist-info/licenses/LICENSE
webhaak-0.6.0.dist-info/METADATA
webhaak-0.6.0.dist-info/WHEEL
webhaak-0.6.0.dist-info/entry_points.txt
webhaak-0.6.0.dist-info/top_level.txt
webhaak-0.6.0.dist-info/RECORD
