Metadata-Version: 2.4
Name: webhaak
Version: 0.6.0
Summary: Simple webhook service to update and deploy sites and do other maintenance and automatic tasks
Author-email: Michiel Scholten <michiel@diginaut.net>
License: Apache
Project-URL: Homepage, https://github.com/aquatix/webhaak
Project-URL: Bug Tracker, https://github.com/aquatix/webhaak/issues
Keywords: webhook,api,automation,CI/CD,Git,monitoring
Classifier: Framework :: FastAPI
Classifier: Programming Language :: Python :: 3
Classifier: License :: OSI Approved :: Apache Software License
Requires-Python: >=3.8
License-File: LICENSE
Requires-Dist: fastapi[all]
Requires-Dist: pydantic>2.0
Requires-Dist: strictyaml
Requires-Dist: gitpython
Requires-Dist: rq
Dynamic: license-file
